{
  "symbol": "HSL",
  "last_updated": "2025-11-21T13:23:29.295147",
  "data_source": "vietcap",
  "total_quarters": 20,
  "financial_stats": [
    {
      "year": "2021",
      "quarter": 4,
      "ratioTTMId": 2765606,
      "ratioType": "RATIO_TTM",
      "organCode": "HHSLAGRI",
      "yearReport": 2021,
      "numberOfSharesMktCap": 32167144,
      "marketCap": 279854152800.0,
      "dividendYield": 0.0,
      "pe": 10.3855644591,
      "pb": 1.0786501164,
      "ps": 0.9170742791,
      "priceToCashFlow": -81.0173382336,
      "evToEbitda": 14.2876577007,
      "cashRatio": 0.8314768371,
      "quickRatio": 4.3176841744,
      "currentRatio": 5.3750371981,
      "ownersEquity": 0.0,
      "debtPerEquity": 0.03884792,
      "debtToEquity": 0.1061800529,
      "roe": 0.0590185153,
      "roa": 0.054037498,
      "daySaleOutstanding": 91.2157601944,
      "daysInventoryOutstanding": 45.4316247206,
      "daysPayableOutstanding": 12.1460546173,
      "grossMargin": 0.0677603976,
      "ebitMargin": 0.0598746396,
      "preTaxProfitMargin": 0.0587333532,
      "afterTaxProfitMargin": 0.0554609913,
      "assetTurnover": 0.9891921042,
      "netInterestMargin": 0.0,
      "averageYieldOnEarningAssets": 0.0,
      "averageCostOfFinancing": 0.0,
      "nonAndInterestIncome": 0.0,
      "costToIncome": 0.0,
      "loansGrowth": 0.0,
      "depositGrowth": 0.0,
      "equityToLiabilities": 0.0,
      "equityToLoans": 0.0,
      "totalEquityTotalAsset": 0.0,
      "ldrLoanDepositRatio": 0.0,
      "npl": 0.0,
      "loansLossReservesToNPLs": 0.0,
      "loansLossReserveToLoans": 0.0,
      "provisionToOutstandingLoans": 0.0,
      "ebit": 16185388318.0,
      "ebitda": 17497756401.0,
      "roic": 0.0616161807,
      "cashCycle": 189.2977241335,
      "fixedAssetTurnover": 25.3092466691,
      "financialLeverage": 0.1061800529,
      "cir": 0.0,
      "car": null,
      "equity": null,
      "casaRatio": null,
      "nob66": null,
      "nob69": null,
      "nob70": null,
      "bsb113": 0.0,
      "ratioYearId": null
    },
    {
      "year": "2021",
      "quarter": 5,
      "ratioTTMId": 12262926,
      "ratioType": "RATIO_YEAR",
      "organCode": "HHSLAGRI",
      "yearReport": 2021,
      "numberOfSharesMktCap": 32167144,
      "marketCap": 279854152800.0,
      "dividendYield": 0.0,
      "pe": 4.8912964467,
      "pb": 0.289153415,
      "ps": 0.2458398285,
      "priceToCashFlow": -36.6077558112,
      "evToEbitda": 5.6786318253,
      "cashRatio": 0.0878861029,
      "quickRatio": 2.3538176679,
      "currentRatio": 2.5485260903,
      "ownersEquity": 0.0,
      "debtPerEquity": 0.1445205189,
      "debtToEquity": 0.2497282711,
      "roe": 0.0629784438,
      "roa": 0.0544852321,
      "daySaleOutstanding": 129.5002414283,
      "daysInventoryOutstanding": 19.1290219845,
      "daysPayableOutstanding": 15.2113921966,
      "grossMargin": 0.0649571068,
      "ebitMargin": 0.0571024686,
      "preTaxProfitMargin": 0.0560238332,
      "afterTaxProfitMargin": 0.0531687698,
      "assetTurnover": 1.0400442123,
      "netInterestMargin": 0.0,
      "averageYieldOnEarningAssets": 0.0,
      "averageCostOfFinancing": 0.0,
      "nonAndInterestIncome": 0.0,
      "costToIncome": 0.0,
      "loansGrowth": 0.0,
      "depositGrowth": 0.0,
      "equityToLiabilities": 0.0,
      "equityToLoans": 0.0,
      "totalEquityTotalAsset": 0.0,
      "ldrLoanDepositRatio": 0.0,
      "npl": 0.0,
      "loansLossReservesToNPLs": 0.0,
      "loansLossReserveToLoans": 0.0,
      "provisionToOutstandingLoans": 0.0,
      "ebit": 17425374721.0,
      "ebitda": 18860074623.0,
      "roic": 0.0581744227,
      "cashCycle": 182.8764809335,
      "fixedAssetTurnover": 26.5298046384,
      "financialLeverage": 0.2497282711,
      "cir": 0.0,
      "car": null,
      "equity": null,
      "casaRatio": null,
      "nob66": null,
      "nob69": null,
      "nob70": null,
      "bsb113": 0.0,
      "ratioYearId": 12262926
    },
    {
      "year": "2022",
      "quarter": 1,
      "ratioTTMId": 2770169,
      "ratioType": "RATIO_TTM",
      "organCode": "HHSLAGRI",
      "yearReport": 2022,
      "numberOfSharesMktCap": 32167144,
      "marketCap": 201044650000.0,
      "dividendYield": 0.0,
      "pe": 8.7858633869,
      "pb": 0.4884332223,
      "ps": 0.6823685373,
      "priceToCashFlow": -0.7013816488,
      "evToEbitda": 10.645933297,
      "cashRatio": 0.0878861029,
      "quickRatio": 2.3662145502,
      "currentRatio": 2.5485260903,
      "ownersEquity": 0.0,
      "debtPerEquity": 0.1445205189,
      "debtToEquity": 0.2497282711,
      "roe": 0.0629784438,
      "roa": 0.0544852321,
      "daySaleOutstanding": 129.5002414283,
      "daysInventoryOutstanding": 19.1290219845,
      "daysPayableOutstanding": 15.2113921966,
      "grossMargin": 0.0649571068,
      "ebitMargin": 0.0571024686,
      "preTaxProfitMargin": 0.0560238332,
      "afterTaxProfitMargin": 0.0531687698,
      "assetTurnover": 1.0400442123,
      "netInterestMargin": 0.0,
      "averageYieldOnEarningAssets": 0.0,
      "averageCostOfFinancing": 0.0,
      "nonAndInterestIncome": 0.0,
      "costToIncome": 0.0,
      "loansGrowth": 0.0,
      "depositGrowth": 0.0,
      "equityToLiabilities": 0.0,
      "equityToLoans": 0.0,
      "totalEquityTotalAsset": 0.0,
      "ldrLoanDepositRatio": 0.0,
      "npl": 0.0,
      "loansLossReservesToNPLs": 0.0,
      "loansLossReserveToLoans": 0.0,
      "provisionToOutstandingLoans": 0.0,
      "ebit": 17425374721.0,
      "ebitda": 18860074623.0,
      "roic": 0.0581744227,
      "cashCycle": 182.8764809335,
      "fixedAssetTurnover": 26.5298046384,
      "financialLeverage": 0.2497282711,
      "cir": 0.0,
      "car": null,
      "equity": null,
      "casaRatio": null,
      "nob66": null,
      "nob69": null,
      "nob70": null,
      "bsb113": 0.0,
      "ratioYearId": null
    },
    {
      "year": "2022",
      "quarter": 2,
      "ratioTTMId": 2777538,
      "ratioType": "RATIO_TTM",
      "organCode": "HHSLAGRI",
      "yearReport": 2022,
      "numberOfSharesMktCap": 35383508,
      "marketCap": 201332160520.0,
      "dividendYield": 0.0,
      "pe": 8.3767722924,
      "pb": 0.484645219,
      "ps": 0.5170180817,
      "priceToCashFlow": 5.5906009105,
      "evToEbitda": 9.6554199309,
      "cashRatio": 0.2527196728,
      "quickRatio": 5.994459264,
      "currentRatio": 7.327863664,
      "ownersEquity": 0.0,
      "debtPerEquity": 0.018411752,
      "debtToEquity": 0.1302976657,
      "roe": 0.0501069051,
      "roa": 0.0425690573,
      "daySaleOutstanding": 137.5500714347,
      "daysInventoryOutstanding": 44.3468847229,
      "daysPayableOutstanding": 32.8733909461,
      "grossMargin": 0.0556962189,
      "ebitMargin": 0.0476143364,
      "preTaxProfitMargin": 0.0474991484,
      "afterTaxProfitMargin": 0.0441314669,
      "assetTurnover": 0.9807409115,
      "netInterestMargin": 0.0,
      "averageYieldOnEarningAssets": 0.0,
      "averageCostOfFinancing": 0.0,
      "nonAndInterestIncome": 0.0,
      "costToIncome": 0.0,
      "loansGrowth": 0.0,
      "depositGrowth": 0.0,
      "equityToLiabilities": 0.0,
      "equityToLoans": 0.0,
      "totalEquityTotalAsset": 0.0,
      "ldrLoanDepositRatio": 0.0,
      "npl": 0.0,
      "loansLossReservesToNPLs": 0.0,
      "loansLossReserveToLoans": 0.0,
      "provisionToOutstandingLoans": 0.0,
      "ebit": 18541512479.0,
      "ebitda": 20639335697.0,
      "roic": 0.0434041083,
      "cashCycle": 290.1128368396,
      "fixedAssetTurnover": 22.6470108207,
      "financialLeverage": 0.1302976657,
      "cir": 0.0,
      "car": null,
      "equity": null,
      "casaRatio": null,
      "nob66": null,
      "nob69": null,
      "nob70": null,
      "bsb113": 0.0,
      "ratioYearId": null
    },
    {
      "year": "2022",
      "quarter": 3,
      "ratioTTMId": 2779818,
      "ratioType": "RATIO_TTM",
      "organCode": "HHSLAGRI",
      "yearReport": 2022,
      "numberOfSharesMktCap": 35383508,
      "marketCap": 169840838400.0,
      "dividendYield": 0.0,
      "pe": 7.5529822304,
      "pb": 0.4057813286,
      "ps": 0.3703142775,
      "priceToCashFlow": -6.2749429559,
      "evToEbitda": 6.6453696563,
      "cashRatio": 0.1161438166,
      "quickRatio": 5.4963873748,
      "currentRatio": 6.6928848229,
      "ownersEquity": 0.0,
      "debtPerEquity": 0.0052524314,
      "debtToEquity": 0.114507491,
      "roe": 0.0480541731,
      "roa": 0.0410205447,
      "daySaleOutstanding": 129.961433957,
      "daysInventoryOutstanding": 43.6401321054,
      "daysPayableOutstanding": 33.1611122786,
      "grossMargin": 0.0506678052,
      "ebitMargin": 0.0430457864,
      "preTaxProfitMargin": 0.043735778,
      "afterTaxProfitMargin": 0.0405109534,
      "assetTurnover": 1.0308931369,
      "netInterestMargin": 0.0,
      "averageYieldOnEarningAssets": 0.0,
      "averageCostOfFinancing": 0.0,
      "nonAndInterestIncome": 0.0,
      "costToIncome": 0.0,
      "loansGrowth": 0.0,
      "depositGrowth": 0.0,
      "equityToLiabilities": 0.0,
      "equityToLoans": 0.0,
      "totalEquityTotalAsset": 0.0,
      "ldrLoanDepositRatio": 0.0,
      "npl": 0.0,
      "loansLossReservesToNPLs": 0.0,
      "loansLossReserveToLoans": 0.0,
      "provisionToOutstandingLoans": 0.0,
      "ebit": 19742507616.0,
      "ebitda": 25664261211.0,
      "roic": 0.0464659257,
      "cashCycle": 290.5850644565,
      "fixedAssetTurnover": 24.2022880249,
      "financialLeverage": 0.114507491,
      "cir": 0.0,
      "car": null,
      "equity": null,
      "casaRatio": null,
      "nob66": null,
      "nob69": null,
      "nob70": null,
      "bsb113": 0.0,
      "ratioYearId": null
    },
    {
      "year": "2022",
      "quarter": 4,
      "ratioTTMId": 2783125,
      "ratioType": "RATIO_TTM",
      "organCode": "HHSLAGRI",
      "yearReport": 2022,
      "numberOfSharesMktCap": 35383508,
      "marketCap": 182578901280.0,
      "dividendYield": 0.0,
      "pe": 10.8325941449,
      "pb": 0.4307158003,
      "ps": 0.391686396,
      "priceToCashFlow": 1.7191823672,
      "evToEbitda": 10.9058330237,
      "cashRatio": 0.078772869,
      "quickRatio": 5.7114425734,
      "currentRatio": 6.84625733,
      "ownersEquity": 0.0343648148,
      "debtPerEquity": 0.0389370987,
      "debtToEquity": 0.1387273238,
      "roe": 0.0448884978,
      "roa": 0.0380159892,
      "daySaleOutstanding": 116.7336505008,
      "daysInventoryOutstanding": 25.5514934931,
      "daysPayableOutstanding": 20.5632044636,
      "grossMargin": 0.0387250818,
      "ebitMargin": 0.0306071684,
      "preTaxProfitMargin": 0.0368264752,
      "afterTaxProfitMargin": 0.0337417009,
      "assetTurnover": 1.1428989775,
      "netInterestMargin": 0.0,
      "averageYieldOnEarningAssets": 0.0,
      "averageCostOfFinancing": 0.0,
      "nonAndInterestIncome": 0.0,
      "costToIncome": 0.0,
      "loansGrowth": 0.0,
      "depositGrowth": 0.0,
      "equityToLiabilities": 0.0,
      "equityToLoans": 0.0,
      "totalEquityTotalAsset": 0.0,
      "ldrLoanDepositRatio": 0.0,
      "npl": 0.0,
      "loansLossReservesToNPLs": 0.0,
      "loansLossReserveToLoans": 0.0,
      "provisionToOutstandingLoans": 0.0,
      "ebit": 14267085166.0,
      "ebitda": 16806287533.0,
      "roic": 0.0320022258,
      "cashCycle": 201.7375515737,
      "fixedAssetTurnover": 14.798037844,
      "financialLeverage": 0.1387273238,
      "cir": 0.0,
      "car": null,
      "equity": null,
      "casaRatio": null,
      "nob66": null,
      "nob69": null,
      "nob70": null,
      "bsb113": 0.0,
      "ratioYearId": null
    },
    {
      "year": "2022",
      "quarter": 5,
      "ratioTTMId": 12273314,
      "ratioType": "RATIO_YEAR",
      "organCode": "HHSLAGRI",
      "yearReport": 2022,
      "numberOfSharesMktCap": 35383508,
      "marketCap": 182578901280.0,
      "dividendYield": 0.0,
      "pe": 23.0489798666,
      "pb": 0.8430677486,
      "ps": 0.7666729844,
      "priceToCashFlow": 3.6579788034,
      "evToEbitda": 22.0485314052,
      "cashRatio": 0.078772869,
      "quickRatio": 5.647697546,
      "currentRatio": 6.84625733,
      "ownersEquity": 0.0343648148,
      "debtPerEquity": 0.0389370987,
      "debtToEquity": 0.1387273238,
      "roe": 0.0453795888,
      "roa": 0.0380159892,
      "daySaleOutstanding": 116.7336505008,
      "daysInventoryOutstanding": 25.5514934931,
      "daysPayableOutstanding": 20.5632044636,
      "grossMargin": 0.0387250818,
      "ebitMargin": 0.0306071684,
      "preTaxProfitMargin": 0.0368264752,
      "afterTaxProfitMargin": 0.0337417009,
      "assetTurnover": 1.1428989775,
      "netInterestMargin": 0.0,
      "averageYieldOnEarningAssets": 0.0,
      "averageCostOfFinancing": 0.0,
      "nonAndInterestIncome": 0.0,
      "costToIncome": 0.0,
      "loansGrowth": 0.0,
      "depositGrowth": 0.0,
      "equityToLiabilities": 0.0,
      "equityToLoans": 0.0,
      "totalEquityTotalAsset": 0.0,
      "ldrLoanDepositRatio": 0.0,
      "npl": 0.0,
      "loansLossReservesToNPLs": 0.0,
      "loansLossReserveToLoans": 0.0,
      "provisionToOutstandingLoans": 0.0,
      "ebit": 14267085166.0,
      "ebitda": 16806287533.0,
      "roic": 0.0320022258,
      "cashCycle": 201.7375515737,
      "fixedAssetTurnover": 14.798037844,
      "financialLeverage": 0.1387273238,
      "cir": 0.0,
      "car": null,
      "equity": null,
      "casaRatio": null,
      "nob66": null,
      "nob69": null,
      "nob70": null,
      "bsb113": 0.0,
      "ratioYearId": 12273314
    },
    {
      "year": "2023",
      "quarter": 1,
      "ratioTTMId": 2795498,
      "ratioType": "RATIO_TTM",
      "organCode": "HHSLAGRI",
      "yearReport": 2023,
      "numberOfSharesMktCap": 35383508,
      "marketCap": 217608574200.0,
      "dividendYield": 0.0,
      "pe": 14.4890703844,
      "pb": 0.5102804158,
      "ps": 0.4236351701,
      "priceToCashFlow": 1.0181313852,
      "evToEbitda": 12.7237076797,
      "cashRatio": 0.5970928498,
      "quickRatio": 8.6442936473,
      "currentRatio": 9.685205013,
      "ownersEquity": 0.0323344364,
      "debtPerEquity": 0.0368786391,
      "debtToEquity": 0.1024500028,
      "roe": 0.0356698978,
      "roa": 0.0314502564,
      "daySaleOutstanding": 109.9661312239,
      "daysInventoryOutstanding": 38.3439834478,
      "daysPayableOutstanding": 22.2385404103,
      "grossMargin": 0.0363528071,
      "ebitMargin": 0.0290797883,
      "preTaxProfitMargin": 0.0334567079,
      "afterTaxProfitMargin": 0.0297997062,
      "assetTurnover": 1.075654268,
      "netInterestMargin": 0.0,
      "averageYieldOnEarningAssets": 0.0,
      "averageCostOfFinancing": 0.0,
      "nonAndInterestIncome": 0.0,
      "costToIncome": 0.0,
      "loansGrowth": 0.0,
      "depositGrowth": 0.0,
      "equityToLiabilities": 0.0,
      "equityToLoans": 0.0,
      "totalEquityTotalAsset": 0.0,
      "ldrLoanDepositRatio": 0.0,
      "npl": 0.0,
      "loansLossReservesToNPLs": 0.0,
      "loansLossReserveToLoans": 0.0,
      "provisionToOutstandingLoans": 0.0,
      "ebit": 14937407734.0,
      "ebitda": 17350709724.0,
      "roic": 0.0333661425,
      "cashCycle": 250.0973149867,
      "fixedAssetTurnover": 14.9065957045,
      "financialLeverage": 0.1024500028,
      "cir": 0.0,
      "car": null,
      "equity": null,
      "casaRatio": null,
      "nob66": null,
      "nob69": null,
      "nob70": null,
      "bsb113": 0.0,
      "ratioYearId": null
    },
    {
      "year": "2023",
      "quarter": 2,
      "ratioTTMId": 2799084,
      "ratioType": "RATIO_TTM",
      "organCode": "HHSLAGRI",
      "yearReport": 2023,
      "numberOfSharesMktCap": 35383508,
      "marketCap": 318451572000.0,
      "dividendYield": 0.0,
      "pe": 26.5636470618,
      "pb": 0.7437372385,
      "ps": 0.7054662612,
      "priceToCashFlow": 25.5030408226,
      "evToEbitda": 16.5783043861,
      "cashRatio": 1.0867553338,
      "quickRatio": 7.4526681793,
      "currentRatio": 9.3009318431,
      "ownersEquity": 0.0283244269,
      "debtPerEquity": 0.0316895826,
      "debtToEquity": 0.0903605646,
      "roe": 0.0282582468,
      "roa": 0.0251235403,
      "daySaleOutstanding": 106.8412270492,
      "daysInventoryOutstanding": 38.7445631924,
      "daysPayableOutstanding": 20.654568356,
      "grossMargin": 0.0356887672,
      "ebitMargin": 0.0267903185,
      "preTaxProfitMargin": 0.0300926654,
      "afterTaxProfitMargin": 0.0271120949,
      "assetTurnover": 0.9460025168,
      "netInterestMargin": 0.0,
      "averageYieldOnEarningAssets": 0.0,
      "averageCostOfFinancing": 0.0,
      "nonAndInterestIncome": 0.0,
      "costToIncome": 0.0,
      "loansGrowth": 0.0,
      "depositGrowth": 0.0,
      "equityToLiabilities": 0.0,
      "equityToLoans": 0.0,
      "totalEquityTotalAsset": 0.0,
      "ldrLoanDepositRatio": 0.0,
      "npl": 0.0,
      "loansLossReservesToNPLs": 0.0,
      "loansLossReserveToLoans": 0.0,
      "provisionToOutstandingLoans": 0.0,
      "ebit": 12093305533.0,
      "ebitda": 18593844103.0,
      "roic": 0.0270420383,
      "cashCycle": 245.8757728807,
      "fixedAssetTurnover": 10.8909372009,
      "financialLeverage": 0.0903605646,
      "cir": 0.0,
      "car": null,
      "equity": null,
      "casaRatio": null,
      "nob66": null,
      "nob69": null,
      "nob70": null,
      "bsb113": 0.0,
      "ratioYearId": null
    },
    {
      "year": "2023",
      "quarter": 3,
      "ratioTTMId": 2800984,
      "ratioType": "RATIO_TTM",
      "organCode": "HHSLAGRI",
      "yearReport": 2023,
      "numberOfSharesMktCap": 35383508,
      "marketCap": 284483404320.0,
      "dividendYield": 0.0,
      "pe": 26.0298948266,
      "pb": 0.6619587424,
      "ps": 0.773856226,
      "priceToCashFlow": 5.0471033463,
      "evToEbitda": 19.2519859884,
      "cashRatio": 0.7558420178,
      "quickRatio": 5.6087645553,
      "currentRatio": 8.209019623,
      "ownersEquity": 0.0277966144,
      "debtPerEquity": 0.0277966144,
      "debtToEquity": 0.1016165052,
      "roe": 0.0255926472,
      "roa": 0.0228113415,
      "daySaleOutstanding": 105.5394822424,
      "daysInventoryOutstanding": 54.4517428535,
      "daysPayableOutstanding": 21.7049198989,
      "grossMargin": 0.0411286693,
      "ebitMargin": 0.0292635363,
      "preTaxProfitMargin": 0.0339029487,
      "afterTaxProfitMargin": 0.0305030471,
      "assetTurnover": 0.7672960425,
      "netInterestMargin": 0.0,
      "averageYieldOnEarningAssets": 0.0,
      "averageCostOfFinancing": 0.0,
      "nonAndInterestIncome": 0.0,
      "costToIncome": 0.0,
      "loansGrowth": 0.0,
      "depositGrowth": 0.0,
      "equityToLiabilities": 0.0,
      "equityToLoans": 0.0,
      "totalEquityTotalAsset": 0.0,
      "ldrLoanDepositRatio": 0.0,
      "npl": 0.0,
      "loansLossReservesToNPLs": 0.0,
      "loansLossReserveToLoans": 0.0,
      "provisionToOutstandingLoans": 0.0,
      "ebit": 10757799892.0,
      "ebitda": 14398108226.0,
      "roic": 0.0240817533,
      "cashCycle": 278.8895442756,
      "fixedAssetTurnover": 7.6190299315,
      "financialLeverage": 0.1016165052,
      "cir": 0.0,
      "car": null,
      "equity": null,
      "casaRatio": null,
      "nob66": null,
      "nob69": null,
      "nob70": null,
      "bsb113": 0.0,
      "ratioYearId": null
    },
    {
      "year": "2023",
      "quarter": 4,
      "ratioTTMId": 2805011,
      "ratioType": "RATIO_TTM",
      "organCode": "HHSLAGRI",
      "yearReport": 2023,
      "numberOfSharesMktCap": 35383508,
      "marketCap": 195316964160.0,
      "dividendYield": 0.0,
      "pe": 16.6159678891,
      "pb": 0.4487535939,
      "ps": 0.5011549751,
      "priceToCashFlow": 490.4024503109,
      "evToEbitda": 9.8140465538,
      "cashRatio": 2.0097224163,
      "quickRatio": 7.8907230935,
      "currentRatio": 8.378467975,
      "ownersEquity": 0.0185739523,
      "debtPerEquity": 0.0261926595,
      "debtToEquity": 0.0909081968,
      "roe": 0.0273640601,
      "roa": 0.0242678831,
      "daySaleOutstanding": 127.1815201431,
      "daysInventoryOutstanding": 32.6056652292,
      "daysPayableOutstanding": 24.9360491857,
      "grossMargin": 0.0476192801,
      "ebitMargin": 0.0354164142,
      "preTaxProfitMargin": 0.0332526599,
      "afterTaxProfitMargin": 0.0309504172,
      "assetTurnover": 0.8046101248,
      "netInterestMargin": 0.0,
      "averageYieldOnEarningAssets": 0.0,
      "averageCostOfFinancing": 0.0,
      "nonAndInterestIncome": 0.0,
      "costToIncome": 0.0,
      "loansGrowth": 0.0,
      "depositGrowth": 0.0,
      "equityToLiabilities": 0.0,
      "equityToLoans": 0.0,
      "totalEquityTotalAsset": 0.0,
      "ldrLoanDepositRatio": 0.0,
      "npl": 0.0,
      "loansLossReservesToNPLs": 0.0,
      "loansLossReserveToLoans": 0.0,
      "provisionToOutstandingLoans": 0.0,
      "ebit": 13802968823.0,
      "ebitda": 19158838980.0,
      "roic": 0.0305623053,
      "cashCycle": 260.5926115783,
      "fixedAssetTurnover": 8.0935570336,
      "financialLeverage": 0.0909081968,
      "cir": 0.0,
      "car": null,
      "equity": null,
      "casaRatio": null,
      "nob66": null,
      "nob69": null,
      "nob70": null,
      "bsb113": 0.0,
      "ratioYearId": null
    },
    {
      "year": "2023",
      "quarter": 5,
      "ratioTTMId": 12276560,
      "ratioType": "RATIO_YEAR",
      "organCode": "HHSLAGRI",
      "yearReport": 2023,
      "numberOfSharesMktCap": 35383508,
      "marketCap": 195316964160.0,
      "dividendYield": 0.0,
      "pe": 12.2512661791,
      "pb": 0.3308744796,
      "ps": 0.3695110052,
      "priceToCashFlow": 361.5829660807,
      "evToEbitda": 4.7860145644,
      "cashRatio": 2.0097224163,
      "quickRatio": 7.8090104907,
      "currentRatio": 8.378467975,
      "ownersEquity": 0.0185739523,
      "debtPerEquity": 0.0261926595,
      "debtToEquity": 0.0909081968,
      "roe": 0.0273640601,
      "roa": 0.0242678831,
      "daySaleOutstanding": 127.1815201431,
      "daysInventoryOutstanding": 32.6056652292,
      "daysPayableOutstanding": 24.9360491857,
      "grossMargin": 0.0476192801,
      "ebitMargin": 0.0354164142,
      "preTaxProfitMargin": 0.0332526599,
      "afterTaxProfitMargin": 0.0309504172,
      "assetTurnover": 0.8046101248,
      "netInterestMargin": 0.0,
      "averageYieldOnEarningAssets": 0.0,
      "averageCostOfFinancing": 0.0,
      "nonAndInterestIncome": 0.0,
      "costToIncome": 0.0,
      "loansGrowth": 0.0,
      "depositGrowth": 0.0,
      "equityToLiabilities": 0.0,
      "equityToLoans": 0.0,
      "totalEquityTotalAsset": 0.0,
      "ldrLoanDepositRatio": 0.0,
      "npl": 0.0,
      "loansLossReservesToNPLs": 0.0,
      "loansLossReserveToLoans": 0.0,
      "provisionToOutstandingLoans": 0.0,
      "ebit": 13802968823.0,
      "ebitda": 19158838980.0,
      "roic": 0.0305623053,
      "cashCycle": 260.5926115783,
      "fixedAssetTurnover": 8.0935570336,
      "financialLeverage": 0.0909081968,
      "cir": 0.0,
      "car": null,
      "equity": null,
      "casaRatio": null,
      "nob66": null,
      "nob69": null,
      "nob70": null,
      "bsb113": 0.0,
      "ratioYearId": 12276560
    },
    {
      "year": "2024",
      "quarter": 1,
      "ratioTTMId": 2808546,
      "ratioType": "RATIO_TTM",
      "organCode": "HHSLAGRI",
      "yearReport": 2024,
      "numberOfSharesMktCap": 35383508,
      "marketCap": 190009437960.0,
      "dividendYield": 0.0,
      "pe": 16.9608023701,
      "pb": 0.4346224799,
      "ps": 0.589438073,
      "priceToCashFlow": -8.4219527591,
      "evToEbitda": 8.5411220246,
      "cashRatio": 2.3666204041,
      "quickRatio": 12.6164542355,
      "currentRatio": 13.139775921,
      "ownersEquity": 0.0198698846,
      "debtPerEquity": 0.0262012634,
      "debtToEquity": 0.0707962357,
      "roe": 0.0258969014,
      "roa": 0.0235231592,
      "daySaleOutstanding": 92.3936007588,
      "daysInventoryOutstanding": 47.98963413,
      "daysPayableOutstanding": 18.7205259551,
      "grossMargin": 0.054035125,
      "ebitMargin": 0.0383983332,
      "preTaxProfitMargin": 0.0382031862,
      "afterTaxProfitMargin": 0.0356435804,
      "assetTurnover": 0.676867803,
      "netInterestMargin": 0.0,
      "averageYieldOnEarningAssets": 0.0,
      "averageCostOfFinancing": 0.0,
      "nonAndInterestIncome": 0.0,
      "costToIncome": 0.0,
      "loansGrowth": 0.0,
      "depositGrowth": 0.0,
      "equityToLiabilities": 0.0,
      "equityToLoans": 0.0,
      "totalEquityTotalAsset": 0.0,
      "ldrLoanDepositRatio": 0.0,
      "npl": 0.0,
      "loansLossReservesToNPLs": 0.0,
      "loansLossReserveToLoans": 0.0,
      "provisionToOutstandingLoans": 0.0,
      "ebit": 12377968164.0,
      "ebitda": 17958993378.0,
      "roic": 0.0272831515,
      "cashCycle": 267.0901390747,
      "fixedAssetTurnover": 6.8393442911,
      "financialLeverage": 0.0707962357,
      "cir": 0.0,
      "car": null,
      "equity": null,
      "casaRatio": null,
      "nob66": null,
      "nob69": null,
      "nob70": null,
      "bsb113": 0.0,
      "ratioYearId": null
    },
    {
      "year": "2024",
      "quarter": 2,
      "ratioTTMId": 2810907,
      "ratioType": "RATIO_TTM",
      "organCode": "HHSLAGRI",
      "yearReport": 2024,
      "numberOfSharesMktCap": 38567363,
      "marketCap": 172010438980.0,
      "dividendYield": 0.0,
      "pe": 14.4334412541,
      "pb": 0.3912744585,
      "ps": 0.5832709393,
      "priceToCashFlow": 5.3650259039,
      "evToEbitda": 9.2156266904,
      "cashRatio": 1.1326177863,
      "quickRatio": 13.1501406782,
      "currentRatio": 14.0994783948,
      "ownersEquity": 0.0142408988,
      "debtPerEquity": 0.0241125607,
      "debtToEquity": 0.0563629025,
      "roe": 0.0273679695,
      "roa": 0.0250627336,
      "daySaleOutstanding": 104.8883978076,
      "daysInventoryOutstanding": 42.2873619267,
      "daysPayableOutstanding": 17.277880375,
      "grossMargin": 0.0606710208,
      "ebitMargin": 0.0430525893,
      "preTaxProfitMargin": 0.0443686302,
      "afterTaxProfitMargin": 0.0415206394,
      "assetTurnover": 0.620194611,
      "netInterestMargin": 0.0,
      "averageYieldOnEarningAssets": 0.0,
      "averageCostOfFinancing": 0.0,
      "nonAndInterestIncome": 0.0,
      "costToIncome": 0.0,
      "loansGrowth": 0.0,
      "depositGrowth": 0.0,
      "equityToLiabilities": 0.0,
      "equityToLoans": 0.0,
      "totalEquityTotalAsset": 0.0,
      "ldrLoanDepositRatio": 0.0,
      "npl": 0.0,
      "loansLossReservesToNPLs": 0.0,
      "loansLossReserveToLoans": 0.0,
      "provisionToOutstandingLoans": 0.0,
      "ebit": 12696491954.0,
      "ebitda": 18078341917.0,
      "roic": 0.0278840766,
      "cashCycle": 287.2295546711,
      "fixedAssetTurnover": 6.4066982375,
      "financialLeverage": 0.0563629025,
      "cir": 0.0,
      "car": null,
      "equity": null,
      "casaRatio": null,
      "nob66": null,
      "nob69": null,
      "nob70": null,
      "bsb113": 0.0,
      "ratioYearId": null
    },
    {
      "year": "2024",
      "quarter": 3,
      "ratioTTMId": 2814234,
      "ratioType": "RATIO_TTM",
      "organCode": "HHSLAGRI",
      "yearReport": 2024,
      "numberOfSharesMktCap": 38567363,
      "marketCap": 155040799260.0,
      "dividendYield": 0.0,
      "pe": 13.42207694,
      "pb": 0.3516820408,
      "ps": 0.5619838781,
      "priceToCashFlow": 1.6254333585,
      "evToEbitda": 8.9571427931,
      "cashRatio": 1.0117637219,
      "quickRatio": 19.2169988446,
      "currentRatio": 19.504489652,
      "ownersEquity": 0.0197008029,
      "debtPerEquity": 0.0219597624,
      "debtToEquity": 0.0503208629,
      "roe": 0.026358843,
      "roa": 0.0244268382,
      "daySaleOutstanding": 111.9180287838,
      "daysInventoryOutstanding": 17.2226070632,
      "daysPayableOutstanding": 12.7520833351,
      "grossMargin": 0.0618718833,
      "ebitMargin": 0.0437009674,
      "preTaxProfitMargin": 0.0454665588,
      "afterTaxProfitMargin": 0.0428461572,
      "assetTurnover": 0.5833955633,
      "netInterestMargin": 0.0,
      "averageYieldOnEarningAssets": 0.0,
      "averageCostOfFinancing": 0.0,
      "nonAndInterestIncome": 0.0,
      "costToIncome": 0.0,
      "loansGrowth": 0.0,
      "depositGrowth": 0.0,
      "equityToLiabilities": 0.0,
      "equityToLoans": 0.0,
      "totalEquityTotalAsset": 0.0,
      "ldrLoanDepositRatio": 0.0,
      "npl": 0.0,
      "loansLossReservesToNPLs": 0.0,
      "loansLossReserveToLoans": 0.0,
      "provisionToOutstandingLoans": 0.0,
      "ebit": 12056276320.0,
      "ebitda": 17431796568.0,
      "roic": 0.0264573106,
      "cashCycle": 303.675875245,
      "fixedAssetTurnover": 6.1342636071,
      "financialLeverage": 0.0503208629,
      "cir": 0.0,
      "car": null,
      "equity": null,
      "casaRatio": null,
      "nob66": null,
      "nob69": null,
      "nob70": null,
      "bsb113": 0.0,
      "ratioYearId": null
    },
    {
      "year": "2024",
      "quarter": 4,
      "ratioTTMId": 2817144,
      "ratioType": "RATIO_TTM",
      "organCode": "HHSLAGRI",
      "yearReport": 2024,
      "numberOfSharesMktCap": 38567363,
      "marketCap": 142699243100.0,
      "dividendYield": 0.0,
      "pe": 21.1153523607,
      "pb": 0.3231462966,
      "ps": 1.0248027825,
      "priceToCashFlow": 3.3341691291,
      "evToEbitda": 11.9527448486,
      "cashRatio": 7.6015532105,
      "quickRatio": 13.4371264158,
      "currentRatio": 13.6252433863,
      "ownersEquity": 0.0090642691,
      "debtPerEquity": 0.0228796488,
      "debtToEquity": 0.0508644336,
      "roe": 0.0154146863,
      "roa": 0.0142357126,
      "daySaleOutstanding": 172.7973225242,
      "daysInventoryOutstanding": 27.0657753973,
      "daysPayableOutstanding": 30.3857072536,
      "grossMargin": 0.0802810223,
      "ebitMargin": 0.0478317361,
      "preTaxProfitMargin": 0.0530369983,
      "afterTaxProfitMargin": 0.0500991025,
      "assetTurnover": 0.2933170107,
      "netInterestMargin": 0.0,
      "averageYieldOnEarningAssets": 0.0,
      "averageCostOfFinancing": 0.0,
      "nonAndInterestIncome": 0.0,
      "costToIncome": 0.0,
      "loansGrowth": 0.0,
      "depositGrowth": 0.0,
      "equityToLiabilities": 0.0,
      "equityToLoans": 0.0,
      "totalEquityTotalAsset": 0.0,
      "ldrLoanDepositRatio": 0.0,
      "npl": 0.0,
      "loansLossReservesToNPLs": 0.0,
      "loansLossReserveToLoans": 0.0,
      "provisionToOutstandingLoans": 0.0,
      "ebit": 6660357141.0,
      "ebitda": 12030503174.0,
      "roic": 0.0145791793,
      "cashCycle": 439.0431536152,
      "fixedAssetTurnover": 3.1578218097,
      "financialLeverage": 0.0508644336,
      "cir": 0.0,
      "car": null,
      "equity": null,
      "casaRatio": null,
      "nob66": null,
      "nob69": null,
      "nob70": null,
      "bsb113": 0.0,
      "ratioYearId": null
    },
    {
      "year": "2024",
      "quarter": 5,
      "ratioTTMId": 12280219,
      "ratioType": "RATIO_YEAR",
      "organCode": "HHSLAGRI",
      "yearReport": 2024,
      "numberOfSharesMktCap": 38567363,
      "marketCap": 142699243100.0,
      "dividendYield": 0.0,
      "pe": 52.5030383022,
      "pb": 0.8034988996,
      "ps": 2.54815827,
      "priceToCashFlow": 8.2903664831,
      "evToEbitda": 23.6808535985,
      "cashRatio": 7.6015532105,
      "quickRatio": 13.3506793347,
      "currentRatio": 13.6252433863,
      "ownersEquity": 0.0090642691,
      "debtPerEquity": 0.0228796488,
      "debtToEquity": 0.0508644336,
      "roe": 0.0154146863,
      "roa": 0.0142357126,
      "daySaleOutstanding": 172.7973225242,
      "daysInventoryOutstanding": 27.0657753973,
      "daysPayableOutstanding": 30.3857072536,
      "grossMargin": 0.0802810223,
      "ebitMargin": 0.0478317361,
      "preTaxProfitMargin": 0.0530369983,
      "afterTaxProfitMargin": 0.0500991025,
      "assetTurnover": 0.2933170107,
      "netInterestMargin": 0.0,
      "averageYieldOnEarningAssets": 0.0,
      "averageCostOfFinancing": 0.0,
      "nonAndInterestIncome": 0.0,
      "costToIncome": 0.0,
      "loansGrowth": 0.0,
      "depositGrowth": 0.0,
      "equityToLiabilities": 0.0,
      "equityToLoans": 0.0,
      "totalEquityTotalAsset": 0.0,
      "ldrLoanDepositRatio": 0.0,
      "npl": 0.0,
      "loansLossReservesToNPLs": 0.0,
      "loansLossReserveToLoans": 0.0,
      "provisionToOutstandingLoans": 0.0,
      "ebit": 6660357141.0,
      "ebitda": 12030503174.0,
      "roic": 0.0145791793,
      "cashCycle": 439.0431536152,
      "fixedAssetTurnover": 3.1578218097,
      "financialLeverage": 0.0508644336,
      "cir": 0.0,
      "car": null,
      "equity": null,
      "casaRatio": null,
      "nob66": null,
      "nob69": null,
      "nob70": null,
      "bsb113": 0.0,
      "ratioYearId": 12280219
    },
    {
      "year": "2025",
      "quarter": 1,
      "ratioTTMId": 2821300,
      "ratioType": "RATIO_TTM",
      "organCode": "HHSLAGRI",
      "yearReport": 2025,
      "numberOfSharesMktCap": 38567363,
      "marketCap": 236417935190.0,
      "dividendYield": 0.0,
      "pe": 30.7025912758,
      "pb": 0.5319038096,
      "ps": 2.2003983884,
      "priceToCashFlow": -5.3531607265,
      "evToEbitda": 21.9742851656,
      "cashRatio": 3.9484612901,
      "quickRatio": 14.0240995379,
      "currentRatio": 14.0240995379,
      "ownersEquity": 0.0090047884,
      "debtPerEquity": 0.0236312884,
      "debtToEquity": 0.0500082661,
      "roe": 0.0174358095,
      "roa": 0.0163887859,
      "daySaleOutstanding": 143.3573272254,
      "daysInventoryOutstanding": 31.223277859,
      "daysPayableOutstanding": 12.3311759806,
      "grossMargin": 0.0894829289,
      "ebitMargin": 0.0501258245,
      "preTaxProfitMargin": 0.0779537706,
      "afterTaxProfitMargin": 0.073802976,
      "assetTurnover": 0.2286759515,
      "netInterestMargin": 0.0,
      "averageYieldOnEarningAssets": 0.0,
      "averageCostOfFinancing": 0.0,
      "nonAndInterestIncome": 0.0,
      "costToIncome": 0.0,
      "loansGrowth": 0.0,
      "depositGrowth": 0.0,
      "equityToLiabilities": 0.0,
      "equityToLoans": 0.0,
      "totalEquityTotalAsset": 0.0,
      "ldrLoanDepositRatio": 0.0,
      "npl": 0.0,
      "loansLossReservesToNPLs": 0.0,
      "loansLossReserveToLoans": 0.0,
      "provisionToOutstandingLoans": 0.0,
      "ebit": 5385681057.0,
      "ebitda": 10770805653.0,
      "roic": 0.0117030187,
      "cashCycle": 664.794351469,
      "fixedAssetTurnover": 2.5212713355,
      "financialLeverage": 0.0500082661,
      "cir": 0.0,
      "car": null,
      "equity": null,
      "casaRatio": null,
      "nob66": null,
      "nob69": null,
      "nob70": null,
      "bsb113": 0.0,
      "ratioYearId": null
    },
    {
      "year": "2025",
      "quarter": 2,
      "ratioTTMId": 2823701,
      "ratioType": "RATIO_TTM",
      "organCode": "HHSLAGRI",
      "yearReport": 2025,
      "numberOfSharesMktCap": 38567363,
      "marketCap": 339007120770.0,
      "dividendYield": 0.0,
      "pe": 118.5103789309,
      "pb": 0.7668657948,
      "ps": 5.1682740298,
      "priceToCashFlow": -8.2872211605,
      "evToEbitda": 42.189977351,
      "cashRatio": 5.3784736481,
      "quickRatio": 10.3482351883,
      "currentRatio": 10.3482351883,
      "ownersEquity": 0.0,
      "debtPerEquity": 0.0,
      "debtToEquity": 0.046464197,
      "roe": 0.0064682475,
      "roa": 0.0060977027,
      "daySaleOutstanding": 107.1505705267,
      "daysInventoryOutstanding": 22.6547346311,
      "daysPayableOutstanding": 21.7153674008,
      "grossMargin": 0.0910417686,
      "ebitMargin": 0.0313043542,
      "preTaxProfitMargin": 0.1358415399,
      "afterTaxProfitMargin": 0.0463586219,
      "assetTurnover": 0.139822511,
      "netInterestMargin": 0.0,
      "averageYieldOnEarningAssets": 0.0,
      "averageCostOfFinancing": 0.0,
      "nonAndInterestIncome": 0.0,
      "costToIncome": 0.0,
      "loansGrowth": 0.0,
      "depositGrowth": 0.0,
      "equityToLiabilities": 0.0,
      "equityToLoans": 0.0,
      "totalEquityTotalAsset": 0.0,
      "ldrLoanDepositRatio": 0.0,
      "npl": 0.0,
      "loansLossReservesToNPLs": 0.0,
      "loansLossReserveToLoans": 0.0,
      "provisionToOutstandingLoans": 0.0,
      "ebit": 2053373896.0,
      "ebitda": 7320954937.0,
      "roic": 0.004603588,
      "cashCycle": 930.7050616441,
      "fixedAssetTurnover": 1.8695923434,
      "financialLeverage": 0.046464197,
      "cir": 0.0,
      "car": null,
      "equity": null,
      "casaRatio": null,
      "nob66": null,
      "nob69": null,
      "nob70": null,
      "bsb113": 0.0,
      "ratioYearId": null
    },
    {
      "year": "2025",
      "quarter": 3,
      "ratioTTMId": 2825692,
      "ratioType": "RATIO_TTM",
      "organCode": "HHSLAGRI",
      "yearReport": 2025,
      "numberOfSharesMktCap": 38567363,
      "marketCap": 354819739600.0,
      "dividendYield": 0.0,
      "pe": 193.1828718776,
      "pb": 0.8077960833,
      "ps": 6.1732656083,
      "priceToCashFlow": -1.6636084326,
      "evToEbitda": 97.8579372003,
      "cashRatio": 4.5129334165,
      "quickRatio": 14.7525913657,
      "currentRatio": 14.7525913657,
      "ownersEquity": 0.0,
      "debtPerEquity": 0.0,
      "debtToEquity": 0.0509832829,
      "roe": 0.0041568944,
      "roa": 0.0039240003,
      "daySaleOutstanding": 58.2802381805,
      "daysInventoryOutstanding": 23.9724554849,
      "daysPayableOutstanding": 27.9464423188,
      "grossMargin": 0.073217713,
      "ebitMargin": 0.0067979145,
      "preTaxProfitMargin": 0.1509355985,
      "afterTaxProfitMargin": 0.033062576,
      "assetTurnover": 0.1227955658,
      "netInterestMargin": 0.0,
      "averageYieldOnEarningAssets": 0.0,
      "averageCostOfFinancing": 0.0,
      "nonAndInterestIncome": 0.0,
      "costToIncome": 0.0,
      "loansGrowth": 0.0,
      "depositGrowth": 0.0,
      "equityToLiabilities": 0.0,
      "equityToLoans": 0.0,
      "totalEquityTotalAsset": 0.0,
      "ldrLoanDepositRatio": 0.0,
      "npl": 0.0,
      "loansLossReservesToNPLs": 0.0,
      "loansLossReserveToLoans": 0.0,
      "provisionToOutstandingLoans": 0.0,
      "ebit": 390722579.0,
      "ebitda": 3188596233.0,
      "roic": 0.0008847748,
      "cashCycle": 1040.0316416638,
      "fixedAssetTurnover": 1.7775064108,
      "financialLeverage": 0.0509832829,
      "cir": 0.0,
      "car": null,
      "equity": null,
      "casaRatio": null,
      "nob66": null,
      "nob69": null,
      "nob70": null,
      "bsb113": 0.0,
      "ratioYearId": null
    }
  ]
}