{
  "symbol": "MDG",
  "last_updated": "2025-11-21T13:23:29.568165",
  "data_source": "vietcap",
  "total_quarters": 20,
  "financial_stats": [
    {
      "year": "2021",
      "quarter": 4,
      "ratioTTMId": 2765920,
      "ratioType": "RATIO_TTM",
      "organCode": "MDG",
      "yearReport": 2021,
      "numberOfSharesMktCap": 10324781,
      "marketCap": 172423842700.0,
      "dividendYield": 0.0598802395,
      "pe": 10.9715986779,
      "pb": 1.087876418,
      "ps": 0.8177744283,
      "priceToCashFlow": 45.7436547988,
      "evToEbitda": 8.855679145,
      "cashRatio": 0.0134930179,
      "quickRatio": 1.2335728818,
      "currentRatio": 1.3658500467,
      "ownersEquity": 0.0,
      "debtPerEquity": 0.4355759891,
      "debtToEquity": 1.2792676051,
      "roe": 0.0489225933,
      "roa": 0.0214145562,
      "daySaleOutstanding": 158.330145516,
      "daysInventoryOutstanding": 56.3014595836,
      "daysPayableOutstanding": 149.1520449786,
      "grossMargin": 0.1473651059,
      "ebitMargin": 0.0484745746,
      "preTaxProfitMargin": 0.0407876704,
      "afterTaxProfitMargin": 0.0331191788,
      "assetTurnover": 0.6465907958,
      "netInterestMargin": 0.0,
      "averageYieldOnEarningAssets": 0.0,
      "averageCostOfFinancing": 0.0,
      "nonAndInterestIncome": 0.0,
      "costToIncome": 0.0,
      "loansGrowth": 0.0,
      "depositGrowth": 0.0,
      "equityToLiabilities": 0.0,
      "equityToLoans": 0.0,
      "totalEquityTotalAsset": 0.0,
      "ldrLoanDepositRatio": 0.0,
      "npl": 0.0,
      "loansLossReservesToNPLs": 0.0,
      "loansLossReserveToLoans": 0.0,
      "provisionToOutstandingLoans": 0.0,
      "ebit": 10728909662.0,
      "ebitda": 13006203110.0,
      "roic": 0.0504550576,
      "cashCycle": 558.1349080436,
      "fixedAssetTurnover": 9.3785058951,
      "financialLeverage": 1.2792676051,
      "cir": 0.0,
      "car": null,
      "equity": null,
      "casaRatio": null,
      "nob66": null,
      "nob69": null,
      "nob70": null,
      "bsb113": 0.0,
      "ratioYearId": null
    },
    {
      "year": "2021",
      "quarter": 5,
      "ratioTTMId": 12262977,
      "ratioType": "RATIO_YEAR",
      "organCode": "MDG",
      "yearReport": 2021,
      "numberOfSharesMktCap": 10324781,
      "marketCap": 172423842700.0,
      "dividendYield": 0.0840336134,
      "pe": 8.6794413167,
      "pb": 0.8175577476,
      "ps": 0.6145714794,
      "priceToCashFlow": 34.3771395044,
      "evToEbitda": 6.2923441692,
      "cashRatio": 0.1118158608,
      "quickRatio": 1.1701552161,
      "currentRatio": 1.3335729368,
      "ownersEquity": 0.0,
      "debtPerEquity": 0.3812386311,
      "debtToEquity": 1.3239009289,
      "roe": 0.1019340013,
      "roa": 0.0438391119,
      "daySaleOutstanding": 171.8007513138,
      "daysInventoryOutstanding": 65.4332107747,
      "daysPayableOutstanding": 187.0565431217,
      "grossMargin": 0.2263091365,
      "ebitMargin": 0.1109559078,
      "preTaxProfitMargin": 0.0939166995,
      "afterTaxProfitMargin": 0.0745355761,
      "assetTurnover": 0.5881635885,
      "netInterestMargin": 0.0,
      "averageYieldOnEarningAssets": 0.0,
      "averageCostOfFinancing": 0.0,
      "nonAndInterestIncome": 0.0,
      "costToIncome": 0.0,
      "loansGrowth": 0.0,
      "depositGrowth": 0.0,
      "equityToLiabilities": 0.0,
      "equityToLoans": 0.0,
      "totalEquityTotalAsset": 0.0,
      "ldrLoanDepositRatio": 0.0,
      "npl": 0.0,
      "loansLossReservesToNPLs": 0.0,
      "loansLossReserveToLoans": 0.0,
      "provisionToOutstandingLoans": 0.0,
      "ebit": 23394524620.0,
      "ebitda": 26467332054.0,
      "roic": 0.1068630957,
      "cashCycle": 611.1683987525,
      "fixedAssetTurnover": 8.9422743891,
      "financialLeverage": 1.3239009289,
      "cir": 0.0,
      "car": null,
      "equity": null,
      "casaRatio": null,
      "nob66": null,
      "nob69": null,
      "nob70": null,
      "bsb113": 0.0,
      "ratioYearId": 12262977
    },
    {
      "year": "2022",
      "quarter": 1,
      "ratioTTMId": 2769922,
      "ratioType": "RATIO_TTM",
      "organCode": "MDG",
      "yearReport": 2022,
      "numberOfSharesMktCap": 10324781,
      "marketCap": 197203317100.0,
      "dividendYield": 0.0628272251,
      "pe": 13.1429868543,
      "pb": 1.2418355956,
      "ps": 0.9207455549,
      "priceToCashFlow": 4.9099385707,
      "evToEbitda": 8.7413827819,
      "cashRatio": 0.1118158608,
      "quickRatio": 1.1875491058,
      "currentRatio": 1.3335729368,
      "ownersEquity": 0.0,
      "debtPerEquity": 0.3812386311,
      "debtToEquity": 1.3239009289,
      "roe": 0.1019340013,
      "roa": 0.0438391119,
      "daySaleOutstanding": 171.8007513138,
      "daysInventoryOutstanding": 65.4332107747,
      "daysPayableOutstanding": 187.0565431217,
      "grossMargin": 0.2263091365,
      "ebitMargin": 0.1109559078,
      "preTaxProfitMargin": 0.0939166995,
      "afterTaxProfitMargin": 0.0745355761,
      "assetTurnover": 0.5881635885,
      "netInterestMargin": 0.0,
      "averageYieldOnEarningAssets": 0.0,
      "averageCostOfFinancing": 0.0,
      "nonAndInterestIncome": 0.0,
      "costToIncome": 0.0,
      "loansGrowth": 0.0,
      "depositGrowth": 0.0,
      "equityToLiabilities": 0.0,
      "equityToLoans": 0.0,
      "totalEquityTotalAsset": 0.0,
      "ldrLoanDepositRatio": 0.0,
      "npl": 0.0,
      "loansLossReservesToNPLs": 0.0,
      "loansLossReserveToLoans": 0.0,
      "provisionToOutstandingLoans": 0.0,
      "ebit": 23394524620.0,
      "ebitda": 26467332054.0,
      "roic": 0.1068630957,
      "cashCycle": 611.1683987525,
      "fixedAssetTurnover": 8.9422743891,
      "financialLeverage": 1.3239009289,
      "cir": 0.0,
      "car": null,
      "equity": null,
      "casaRatio": null,
      "nob66": null,
      "nob69": null,
      "nob70": null,
      "bsb113": 0.0,
      "ratioYearId": null
    },
    {
      "year": "2022",
      "quarter": 2,
      "ratioTTMId": 2776723,
      "ratioType": "RATIO_TTM",
      "organCode": "MDG",
      "yearReport": 2022,
      "numberOfSharesMktCap": 10324781,
      "marketCap": 172423842700.0,
      "dividendYield": 0.0718562874,
      "pe": 9.4827323233,
      "pb": 1.0951322687,
      "ps": 0.7695438919,
      "priceToCashFlow": 6.2403864927,
      "evToEbitda": 7.5246502374,
      "cashRatio": 0.1090396492,
      "quickRatio": 1.1150315742,
      "currentRatio": 1.307948902,
      "ownersEquity": 0.0,
      "debtPerEquity": 0.5215746328,
      "debtToEquity": 1.4270014013,
      "roe": 0.1167843389,
      "roa": 0.0501355231,
      "daySaleOutstanding": 134.2468427319,
      "daysInventoryOutstanding": 74.6743011151,
      "daysPayableOutstanding": 181.5098703895,
      "grossMargin": 0.2640437377,
      "ebitMargin": 0.1240099246,
      "preTaxProfitMargin": 0.1023665178,
      "afterTaxProfitMargin": 0.0811521264,
      "assetTurnover": 0.6177967886,
      "netInterestMargin": 0.0,
      "averageYieldOnEarningAssets": 0.0,
      "averageCostOfFinancing": 0.0,
      "nonAndInterestIncome": 0.0,
      "costToIncome": 0.0,
      "loansGrowth": 0.0,
      "depositGrowth": 0.0,
      "equityToLiabilities": 0.0,
      "equityToLoans": 0.0,
      "totalEquityTotalAsset": 0.0,
      "ldrLoanDepositRatio": 0.0,
      "npl": 0.0,
      "loansLossReservesToNPLs": 0.0,
      "loansLossReserveToLoans": 0.0,
      "provisionToOutstandingLoans": 0.0,
      "ebit": 27785637634.0,
      "ebitda": 30944138026.0,
      "roic": 0.1159835412,
      "cashCycle": 611.5880612366,
      "fixedAssetTurnover": 9.5596455704,
      "financialLeverage": 1.4270014013,
      "cir": 0.0,
      "car": null,
      "equity": null,
      "casaRatio": null,
      "nob66": null,
      "nob69": null,
      "nob70": null,
      "bsb113": 0.0,
      "ratioYearId": null
    },
    {
      "year": "2022",
      "quarter": 3,
      "ratioTTMId": 2777751,
      "ratioType": "RATIO_TTM",
      "organCode": "MDG",
      "yearReport": 2022,
      "numberOfSharesMktCap": 10324781,
      "marketCap": 131124718700.0,
      "dividendYield": 0.094488189,
      "pe": 5.7146298766,
      "pb": 0.8081802865,
      "ps": 0.4410069491,
      "priceToCashFlow": 3.6445356961,
      "evToEbitda": 4.9197211744,
      "cashRatio": 0.1418724094,
      "quickRatio": 1.1549959926,
      "currentRatio": 1.3267144154,
      "ownersEquity": 0.0,
      "debtPerEquity": 0.5150501534,
      "debtToEquity": 1.4304154976,
      "roe": 0.1441048589,
      "roa": 0.0608868324,
      "daySaleOutstanding": 94.6613594972,
      "daysInventoryOutstanding": 60.4511735296,
      "daysPayableOutstanding": 138.0506383822,
      "grossMargin": 0.2398449813,
      "ebitMargin": 0.1137309007,
      "preTaxProfitMargin": 0.0969777208,
      "afterTaxProfitMargin": 0.0771715682,
      "assetTurnover": 0.7889801111,
      "netInterestMargin": 0.0,
      "averageYieldOnEarningAssets": 0.0,
      "averageCostOfFinancing": 0.0,
      "nonAndInterestIncome": 0.0,
      "costToIncome": 0.0,
      "loansGrowth": 0.0,
      "depositGrowth": 0.0,
      "equityToLiabilities": 0.0,
      "equityToLoans": 0.0,
      "totalEquityTotalAsset": 0.0,
      "ldrLoanDepositRatio": 0.0,
      "npl": 0.0,
      "loansLossReservesToNPLs": 0.0,
      "loansLossReserveToLoans": 0.0,
      "provisionToOutstandingLoans": 0.0,
      "ebit": 33815640305.0,
      "ebitda": 37157122536.0,
      "roic": 0.1375670071,
      "cashCycle": 467.3188935434,
      "fixedAssetTurnover": 12.6677712981,
      "financialLeverage": 1.4304154976,
      "cir": 0.0,
      "car": null,
      "equity": null,
      "casaRatio": null,
      "nob66": null,
      "nob69": null,
      "nob70": null,
      "bsb113": 0.0,
      "ratioYearId": null
    },
    {
      "year": "2022",
      "quarter": 4,
      "ratioTTMId": 2782160,
      "ratioType": "RATIO_TTM",
      "organCode": "MDG",
      "yearReport": 2022,
      "numberOfSharesMktCap": 10324781,
      "marketCap": 163131539800.0,
      "dividendYield": 0.0759493671,
      "pe": 7.542066257,
      "pb": 0.9571293897,
      "ps": 0.4521074815,
      "priceToCashFlow": 45.2513274295,
      "evToEbitda": 6.6749245306,
      "cashRatio": 0.1303348762,
      "quickRatio": 1.2355879494,
      "currentRatio": 1.3734870147,
      "ownersEquity": 0.0,
      "debtPerEquity": 0.4606761674,
      "debtToEquity": 1.3148518358,
      "roe": 0.1315129875,
      "roa": 0.0567058903,
      "daySaleOutstanding": 94.1502050496,
      "daysInventoryOutstanding": 38.9742410013,
      "daysPayableOutstanding": 116.9958734741,
      "grossMargin": 0.1923280349,
      "ebitMargin": 0.0795043822,
      "preTaxProfitMargin": 0.074829886,
      "afterTaxProfitMargin": 0.0599447772,
      "assetTurnover": 0.945968822,
      "netInterestMargin": 0.0,
      "averageYieldOnEarningAssets": 0.0,
      "averageCostOfFinancing": 0.0,
      "nonAndInterestIncome": 0.0,
      "costToIncome": 0.0,
      "loansGrowth": 0.0,
      "depositGrowth": 0.0,
      "equityToLiabilities": 0.0,
      "equityToLoans": 0.0,
      "totalEquityTotalAsset": 0.0,
      "ldrLoanDepositRatio": 0.0,
      "npl": 0.0,
      "loansLossReservesToNPLs": 0.0,
      "loansLossReserveToLoans": 0.0,
      "provisionToOutstandingLoans": 0.0,
      "ebit": 28687143684.0,
      "ebitda": 32181562898.0,
      "roic": 0.1152301379,
      "cashCycle": 391.603151514,
      "fixedAssetTurnover": 15.7127570192,
      "financialLeverage": 1.3148518358,
      "cir": 0.0,
      "car": null,
      "equity": null,
      "casaRatio": null,
      "nob66": null,
      "nob69": null,
      "nob70": null,
      "bsb113": 0.0,
      "ratioYearId": null
    },
    {
      "year": "2022",
      "quarter": 5,
      "ratioTTMId": 12273365,
      "ratioType": "RATIO_YEAR",
      "organCode": "MDG",
      "yearReport": 2022,
      "numberOfSharesMktCap": 10324781,
      "marketCap": 163131539800.0,
      "dividendYield": 0.0427046263,
      "pe": 7.4456976855,
      "pb": 0.8976318932,
      "ps": 0.4240033782,
      "priceToCashFlow": 42.4383945879,
      "evToEbitda": 6.3031366428,
      "cashRatio": 0.1303348762,
      "quickRatio": 1.2220676306,
      "currentRatio": 1.3734870147,
      "ownersEquity": 0.0,
      "debtPerEquity": 0.4606761674,
      "debtToEquity": 1.3148518358,
      "roe": 0.1315129875,
      "roa": 0.0567058903,
      "daySaleOutstanding": 94.1502050496,
      "daysInventoryOutstanding": 38.9742410013,
      "daysPayableOutstanding": 116.9958734741,
      "grossMargin": 0.1923280349,
      "ebitMargin": 0.0795043822,
      "preTaxProfitMargin": 0.074829886,
      "afterTaxProfitMargin": 0.0599447772,
      "assetTurnover": 0.945968822,
      "netInterestMargin": 0.0,
      "averageYieldOnEarningAssets": 0.0,
      "averageCostOfFinancing": 0.0,
      "nonAndInterestIncome": 0.0,
      "costToIncome": 0.0,
      "loansGrowth": 0.0,
      "depositGrowth": 0.0,
      "equityToLiabilities": 0.0,
      "equityToLoans": 0.0,
      "totalEquityTotalAsset": 0.0,
      "ldrLoanDepositRatio": 0.0,
      "npl": 0.0,
      "loansLossReservesToNPLs": 0.0,
      "loansLossReserveToLoans": 0.0,
      "provisionToOutstandingLoans": 0.0,
      "ebit": 28687143684.0,
      "ebitda": 32181562898.0,
      "roic": 0.1152301379,
      "cashCycle": 391.603151514,
      "fixedAssetTurnover": 15.7127570192,
      "financialLeverage": 1.3148518358,
      "cir": 0.0,
      "car": null,
      "equity": null,
      "casaRatio": null,
      "nob66": null,
      "nob69": null,
      "nob70": null,
      "bsb113": 0.0,
      "ratioYearId": 12273365
    },
    {
      "year": "2023",
      "quarter": 1,
      "ratioTTMId": 2795888,
      "ratioType": "RATIO_TTM",
      "organCode": "MDG",
      "yearReport": 2023,
      "numberOfSharesMktCap": 10324781,
      "marketCap": 163131539800.0,
      "dividendYield": 0.0379746835,
      "pe": 7.2415853237,
      "pb": 0.952597361,
      "ps": 0.4356055756,
      "priceToCashFlow": -9.119545418,
      "evToEbitda": 6.6788006422,
      "cashRatio": 0.1109712252,
      "quickRatio": 1.2173638412,
      "currentRatio": 1.4008023984,
      "ownersEquity": 0.0,
      "debtPerEquity": 0.557952113,
      "debtToEquity": 1.2676940632,
      "roe": 0.1361717736,
      "roa": 0.0576879811,
      "daySaleOutstanding": 77.1166052243,
      "daysInventoryOutstanding": 47.6027836514,
      "daysPayableOutstanding": 109.5001179547,
      "grossMargin": 0.2014861701,
      "ebitMargin": 0.0842933776,
      "preTaxProfitMargin": 0.07563435,
      "afterTaxProfitMargin": 0.0601533443,
      "assetTurnover": 0.9590153595,
      "netInterestMargin": 0.0,
      "averageYieldOnEarningAssets": 0.0,
      "averageCostOfFinancing": 0.0,
      "nonAndInterestIncome": 0.0,
      "costToIncome": 0.0,
      "loansGrowth": 0.0,
      "depositGrowth": 0.0,
      "equityToLiabilities": 0.0,
      "equityToLoans": 0.0,
      "totalEquityTotalAsset": 0.0,
      "ldrLoanDepositRatio": 0.0,
      "npl": 0.0,
      "loansLossReservesToNPLs": 0.0,
      "loansLossReserveToLoans": 0.0,
      "provisionToOutstandingLoans": 0.0,
      "ebit": 31567338114.0,
      "ebitda": 35178848320.0,
      "roic": 0.1183192194,
      "cashCycle": 384.0457084759,
      "fixedAssetTurnover": 16.2073917288,
      "financialLeverage": 1.2676940632,
      "cir": 0.0,
      "car": null,
      "equity": null,
      "casaRatio": null,
      "nob66": null,
      "nob69": null,
      "nob70": null,
      "bsb113": 0.0,
      "ratioYearId": null
    },
    {
      "year": "2023",
      "quarter": 2,
      "ratioTTMId": 2798723,
      "ratioType": "RATIO_TTM",
      "organCode": "MDG",
      "yearReport": 2023,
      "numberOfSharesMktCap": 10324781,
      "marketCap": 134222153000.0,
      "dividendYield": 0.0461538462,
      "pe": 7.4683484192,
      "pb": 0.8056190398,
      "ps": 0.363387737,
      "priceToCashFlow": -20.5648569425,
      "evToEbitda": 7.0032450539,
      "cashRatio": 0.0617920047,
      "quickRatio": 1.1744920301,
      "currentRatio": 1.3529061862,
      "ownersEquity": 0.0,
      "debtPerEquity": 0.5641386279,
      "debtToEquity": 1.4200009707,
      "roe": 0.107154579,
      "roa": 0.0454110709,
      "daySaleOutstanding": 85.5217176667,
      "daysInventoryOutstanding": 47.2349597251,
      "daysPayableOutstanding": 119.550376647,
      "grossMargin": 0.193644932,
      "ebitMargin": 0.0724335825,
      "preTaxProfitMargin": 0.0613005496,
      "afterTaxProfitMargin": 0.0486570412,
      "assetTurnover": 0.9332887855,
      "netInterestMargin": 0.0,
      "averageYieldOnEarningAssets": 0.0,
      "averageCostOfFinancing": 0.0,
      "nonAndInterestIncome": 0.0,
      "costToIncome": 0.0,
      "loansGrowth": 0.0,
      "depositGrowth": 0.0,
      "equityToLiabilities": 0.0,
      "equityToLoans": 0.0,
      "totalEquityTotalAsset": 0.0,
      "ldrLoanDepositRatio": 0.0,
      "npl": 0.0,
      "loansLossReservesToNPLs": 0.0,
      "loansLossReserveToLoans": 0.0,
      "provisionToOutstandingLoans": 0.0,
      "ebit": 26754318898.0,
      "ebitda": 30499138479.0,
      "roic": 0.1026654178,
      "cashCycle": 406.3596393145,
      "fixedAssetTurnover": 16.4071338631,
      "financialLeverage": 1.4200009707,
      "cir": 0.0,
      "car": null,
      "equity": null,
      "casaRatio": null,
      "nob66": null,
      "nob69": null,
      "nob70": null,
      "bsb113": 0.0,
      "ratioYearId": null
    },
    {
      "year": "2023",
      "quarter": 3,
      "ratioTTMId": 2802030,
      "ratioType": "RATIO_TTM",
      "organCode": "MDG",
      "yearReport": 2023,
      "numberOfSharesMktCap": 10324781,
      "marketCap": 153839236900.0,
      "dividendYield": 0.0402684564,
      "pe": 11.1389335289,
      "pb": 0.9198959444,
      "ps": 0.4780163818,
      "priceToCashFlow": -8.6965208435,
      "evToEbitda": 9.1171169512,
      "cashRatio": 0.0473510108,
      "quickRatio": 1.1921410415,
      "currentRatio": 1.3818023888,
      "ownersEquity": 0.0,
      "debtPerEquity": 0.5620159088,
      "debtToEquity": 1.302590218,
      "roe": 0.0817367201,
      "roa": 0.0351019616,
      "daySaleOutstanding": 101.081789313,
      "daysInventoryOutstanding": 55.5710187775,
      "daysPayableOutstanding": 139.5041961755,
      "grossMargin": 0.2094376299,
      "ebitMargin": 0.0692109066,
      "preTaxProfitMargin": 0.054376754,
      "afterTaxProfitMargin": 0.0429140169,
      "assetTurnover": 0.817960288,
      "netInterestMargin": 0.0,
      "averageYieldOnEarningAssets": 0.0,
      "averageCostOfFinancing": 0.0,
      "nonAndInterestIncome": 0.0,
      "costToIncome": 0.0,
      "loansGrowth": 0.0,
      "depositGrowth": 0.0,
      "equityToLiabilities": 0.0,
      "equityToLoans": 0.0,
      "totalEquityTotalAsset": 0.0,
      "ldrLoanDepositRatio": 0.0,
      "npl": 0.0,
      "loansLossReservesToNPLs": 0.0,
      "loansLossReserveToLoans": 0.0,
      "provisionToOutstandingLoans": 0.0,
      "ebit": 22274033825.0,
      "ebitda": 26051363145.0,
      "roic": 0.0852677905,
      "cashCycle": 474.3736623873,
      "fixedAssetTurnover": 14.1883011217,
      "financialLeverage": 1.302590218,
      "cir": 0.0,
      "car": null,
      "equity": null,
      "casaRatio": null,
      "nob66": null,
      "nob69": null,
      "nob70": null,
      "bsb113": 0.0,
      "ratioYearId": null
    },
    {
      "year": "2023",
      "quarter": 4,
      "ratioTTMId": 2804871,
      "ratioType": "RATIO_TTM",
      "organCode": "MDG",
      "yearReport": 2023,
      "numberOfSharesMktCap": 10324781,
      "marketCap": 131640957750.0,
      "dividendYield": 0.0470588235,
      "pe": -3.6075993131,
      "pb": 1.0426461725,
      "ps": 0.475233054,
      "priceToCashFlow": -6.4390960672,
      "evToEbitda": -9.0754988521,
      "cashRatio": 0.0692292931,
      "quickRatio": 1.0570164735,
      "currentRatio": 1.1844017981,
      "ownersEquity": 0.0,
      "debtPerEquity": 0.7444255366,
      "debtToEquity": 1.8115443746,
      "roe": -0.2459759264,
      "roa": -0.0973693126,
      "daySaleOutstanding": 127.6619676313,
      "daysInventoryOutstanding": 49.5213101591,
      "daysPayableOutstanding": 164.0357006105,
      "grossMargin": 0.2012357241,
      "ebitMargin": -0.0995669617,
      "preTaxProfitMargin": -0.1314599776,
      "afterTaxProfitMargin": -0.1317311078,
      "assetTurnover": 0.7391520063,
      "netInterestMargin": 0.0,
      "averageYieldOnEarningAssets": 0.0,
      "averageCostOfFinancing": 0.0,
      "nonAndInterestIncome": 0.0,
      "costToIncome": 0.0,
      "loansGrowth": 0.0,
      "depositGrowth": 0.0,
      "equityToLiabilities": 0.0,
      "equityToLoans": 0.0,
      "totalEquityTotalAsset": 0.0,
      "ldrLoanDepositRatio": 0.0,
      "npl": 0.0,
      "loansLossReservesToNPLs": 0.0,
      "loansLossReserveToLoans": 0.0,
      "provisionToOutstandingLoans": 0.0,
      "ebit": -27580342087.0,
      "ebitda": -23724871645.0,
      "roic": -0.1252256034,
      "cashCycle": 520.4197544406,
      "fixedAssetTurnover": 11.9446924455,
      "financialLeverage": 1.8115443746,
      "cir": 0.0,
      "car": null,
      "equity": null,
      "casaRatio": null,
      "nob66": null,
      "nob69": null,
      "nob70": null,
      "bsb113": 0.0,
      "ratioYearId": null
    },
    {
      "year": "2023",
      "quarter": 5,
      "ratioTTMId": 12276609,
      "ratioType": "RATIO_YEAR",
      "organCode": "MDG",
      "yearReport": 2023,
      "numberOfSharesMktCap": 10324781,
      "marketCap": 131640957750.0,
      "dividendYield": 0.0,
      "pe": -3.7003106153,
      "pb": 1.0694410231,
      "ps": 0.4874460166,
      "priceToCashFlow": -6.6045736964,
      "evToEbitda": -8.9854452461,
      "cashRatio": 0.0692292931,
      "quickRatio": 1.0359385114,
      "currentRatio": 1.1844017981,
      "ownersEquity": 0.0,
      "debtPerEquity": 0.7444255366,
      "debtToEquity": 1.8115443746,
      "roe": -0.2459759264,
      "roa": -0.0973693126,
      "daySaleOutstanding": 127.6619676313,
      "daysInventoryOutstanding": 49.5213101591,
      "daysPayableOutstanding": 164.0357006105,
      "grossMargin": 0.2012357241,
      "ebitMargin": -0.0995669617,
      "preTaxProfitMargin": -0.1314599776,
      "afterTaxProfitMargin": -0.1317311078,
      "assetTurnover": 0.7391520063,
      "netInterestMargin": 0.0,
      "averageYieldOnEarningAssets": 0.0,
      "averageCostOfFinancing": 0.0,
      "nonAndInterestIncome": 0.0,
      "costToIncome": 0.0,
      "loansGrowth": 0.0,
      "depositGrowth": 0.0,
      "equityToLiabilities": 0.0,
      "equityToLoans": 0.0,
      "totalEquityTotalAsset": 0.0,
      "ldrLoanDepositRatio": 0.0,
      "npl": 0.0,
      "loansLossReservesToNPLs": 0.0,
      "loansLossReserveToLoans": 0.0,
      "provisionToOutstandingLoans": 0.0,
      "ebit": -27580342087.0,
      "ebitda": -23724871645.0,
      "roic": -0.1252256034,
      "cashCycle": 520.4197544406,
      "fixedAssetTurnover": 11.9446924455,
      "financialLeverage": 1.8115443746,
      "cir": 0.0,
      "car": null,
      "equity": null,
      "casaRatio": null,
      "nob66": null,
      "nob69": null,
      "nob70": null,
      "bsb113": 0.0,
      "ratioYearId": 12276609
    },
    {
      "year": "2024",
      "quarter": 1,
      "ratioTTMId": 2807547,
      "ratioType": "RATIO_TTM",
      "organCode": "MDG",
      "yearReport": 2024,
      "numberOfSharesMktCap": 10324781,
      "marketCap": 120799937700.0,
      "dividendYield": 0.0,
      "pe": -7.5271242838,
      "pb": 1.0904169497,
      "ps": 0.4484778344,
      "priceToCashFlow": -97.91301312,
      "evToEbitda": -51.5022526004,
      "cashRatio": 0.0136689579,
      "quickRatio": 0.970135736,
      "currentRatio": 1.0859541295,
      "ownersEquity": 0.0,
      "debtPerEquity": 0.8108877503,
      "debtToEquity": 2.1922332185,
      "roe": -0.1055611185,
      "roa": -0.0418498559,
      "daySaleOutstanding": 130.6805220736,
      "daysInventoryOutstanding": 54.993653878,
      "daysPayableOutstanding": 149.5364531411,
      "grossMargin": 0.1327128242,
      "ebitMargin": -0.0295974575,
      "preTaxProfitMargin": -0.0597611736,
      "afterTaxProfitMargin": -0.0595815636,
      "assetTurnover": 0.7023960664,
      "netInterestMargin": 0.0,
      "averageYieldOnEarningAssets": 0.0,
      "averageCostOfFinancing": 0.0,
      "nonAndInterestIncome": 0.0,
      "costToIncome": 0.0,
      "loansGrowth": 0.0,
      "depositGrowth": 0.0,
      "equityToLiabilities": 0.0,
      "equityToLoans": 0.0,
      "totalEquityTotalAsset": 0.0,
      "ldrLoanDepositRatio": 0.0,
      "npl": 0.0,
      "loansLossReservesToNPLs": 0.0,
      "loansLossReserveToLoans": 0.0,
      "provisionToOutstandingLoans": 0.0,
      "ebit": -7972235739.0,
      "ebitda": -4025319870.0,
      "roic": -0.0397387759,
      "cashCycle": 540.000339548,
      "fixedAssetTurnover": 11.6821694476,
      "financialLeverage": 2.1922332185,
      "cir": 0.0,
      "car": null,
      "equity": null,
      "casaRatio": null,
      "nob66": null,
      "nob69": null,
      "nob70": null,
      "bsb113": 0.0,
      "ratioYearId": null
    },
    {
      "year": "2024",
      "quarter": 2,
      "ratioTTMId": 2811056,
      "ratioType": "RATIO_TTM",
      "organCode": "MDG",
      "yearReport": 2024,
      "numberOfSharesMktCap": 10324781,
      "marketCap": 115637547200.0,
      "dividendYield": 0.0,
      "pe": -6.7996593685,
      "pb": 1.0302353331,
      "ps": 0.4596527881,
      "priceToCashFlow": 8.6944828528,
      "evToEbitda": -33.4745533643,
      "cashRatio": 0.041598205,
      "quickRatio": 1.0384297407,
      "currentRatio": 1.1206106797,
      "ownersEquity": 0.0,
      "debtPerEquity": 0.7308166017,
      "debtToEquity": 1.8955019901,
      "roe": -0.1228423792,
      "roa": -0.046729303,
      "daySaleOutstanding": 133.7219912608,
      "daysInventoryOutstanding": 48.7524761598,
      "daysPayableOutstanding": 146.5849350635,
      "grossMargin": 0.1364963338,
      "ebitMargin": -0.0383735503,
      "preTaxProfitMargin": -0.070045213,
      "afterTaxProfitMargin": -0.0675993845,
      "assetTurnover": 0.6912681732,
      "netInterestMargin": 0.0,
      "averageYieldOnEarningAssets": 0.0,
      "averageCostOfFinancing": 0.0,
      "nonAndInterestIncome": 0.0,
      "costToIncome": 0.0,
      "loansGrowth": 0.0,
      "depositGrowth": 0.0,
      "equityToLiabilities": 0.0,
      "equityToLoans": 0.0,
      "totalEquityTotalAsset": 0.0,
      "ldrLoanDepositRatio": 0.0,
      "npl": 0.0,
      "loansLossReservesToNPLs": 0.0,
      "loansLossReserveToLoans": 0.0,
      "provisionToOutstandingLoans": 0.0,
      "ebit": -9653859068.0,
      "ebitda": -5640607779.0,
      "roic": -0.0496921138,
      "cashCycle": 536.1345166847,
      "fixedAssetTurnover": 11.0700257341,
      "financialLeverage": 1.8955019901,
      "cir": 0.0,
      "car": null,
      "equity": null,
      "casaRatio": null,
      "nob66": null,
      "nob69": null,
      "nob70": null,
      "bsb113": 0.0,
      "ratioYearId": null
    },
    {
      "year": "2024",
      "quarter": 3,
      "ratioTTMId": 2813567,
      "ratioType": "RATIO_TTM",
      "organCode": "MDG",
      "yearReport": 2024,
      "numberOfSharesMktCap": 10324781,
      "marketCap": 128027284400.0,
      "dividendYield": 0.0,
      "pe": -9.1617683359,
      "pb": 1.1035111618,
      "ps": 0.5336138031,
      "priceToCashFlow": 6.117039243,
      "evToEbitda": -64.4904000732,
      "cashRatio": 0.0614987451,
      "quickRatio": 1.083695364,
      "currentRatio": 1.1696433823,
      "ownersEquity": 0.0,
      "debtPerEquity": 0.6906570361,
      "debtToEquity": 1.7208101329,
      "roe": -0.1112264832,
      "roa": -0.0403198173,
      "daySaleOutstanding": 133.2042754697,
      "daysInventoryOutstanding": 41.0310772256,
      "daysPayableOutstanding": 146.2757025503,
      "grossMargin": 0.1480888848,
      "ebitMargin": -0.0293368946,
      "preTaxProfitMargin": -0.0616201892,
      "afterTaxProfitMargin": -0.0582435381,
      "assetTurnover": 0.6922624999,
      "netInterestMargin": 0.0,
      "averageYieldOnEarningAssets": 0.0,
      "averageCostOfFinancing": 0.0,
      "nonAndInterestIncome": 0.0,
      "costToIncome": 0.0,
      "loansGrowth": 0.0,
      "depositGrowth": 0.0,
      "equityToLiabilities": 0.0,
      "equityToLoans": 0.0,
      "totalEquityTotalAsset": 0.0,
      "ldrLoanDepositRatio": 0.0,
      "npl": 0.0,
      "loansLossReservesToNPLs": 0.0,
      "loansLossReserveToLoans": 0.0,
      "provisionToOutstandingLoans": 0.0,
      "ebit": -7038654043.0,
      "ebitda": -3037321606.0,
      "roic": -0.0358846157,
      "cashCycle": 527.0888571065,
      "fixedAssetTurnover": 11.1122576948,
      "financialLeverage": 1.7208101329,
      "cir": 0.0,
      "car": null,
      "equity": null,
      "casaRatio": null,
      "nob66": null,
      "nob69": null,
      "nob70": null,
      "bsb113": 0.0,
      "ratioYearId": null
    },
    {
      "year": "2024",
      "quarter": 4,
      "ratioTTMId": 2817893,
      "ratioType": "RATIO_TTM",
      "organCode": "MDG",
      "yearReport": 2024,
      "numberOfSharesMktCap": 10324781,
      "marketCap": 153839236900.0,
      "dividendYield": 0.0,
      "pe": 38.6863166904,
      "pb": 1.1812599538,
      "ps": 0.6727522603,
      "priceToCashFlow": 3.8710529678,
      "evToEbitda": 14.6000888343,
      "cashRatio": 0.1200656495,
      "quickRatio": 1.0687429682,
      "currentRatio": 1.1486224539,
      "ownersEquity": 0.0,
      "debtPerEquity": 0.6244968963,
      "debtToEquity": 1.5029975003,
      "roe": 0.0310077086,
      "roa": 0.0116795181,
      "daySaleOutstanding": 135.0984505303,
      "daysInventoryOutstanding": 46.5473863038,
      "daysPayableOutstanding": 167.4609066187,
      "grossMargin": 0.2323671009,
      "ebitMargin": 0.0494368303,
      "preTaxProfitMargin": 0.0177449399,
      "afterTaxProfitMargin": 0.017389928,
      "assetTurnover": 0.6716254464,
      "netInterestMargin": 0.0,
      "averageYieldOnEarningAssets": 0.0,
      "averageCostOfFinancing": 0.0,
      "nonAndInterestIncome": 0.0,
      "costToIncome": 0.0,
      "loansGrowth": 0.0,
      "depositGrowth": 0.0,
      "equityToLiabilities": 0.0,
      "equityToLoans": 0.0,
      "totalEquityTotalAsset": 0.0,
      "ldrLoanDepositRatio": 0.0,
      "npl": 0.0,
      "loansLossReservesToNPLs": 0.0,
      "loansLossReserveToLoans": 0.0,
      "provisionToOutstandingLoans": 0.0,
      "ebit": 11304791812.0,
      "ebitda": 15184156791.0,
      "roic": 0.0534345365,
      "cashCycle": 534.8564984113,
      "fixedAssetTurnover": 10.7441868091,
      "financialLeverage": 1.5029975003,
      "cir": 0.0,
      "car": null,
      "equity": null,
      "casaRatio": null,
      "nob66": null,
      "nob69": null,
      "nob70": null,
      "bsb113": 0.0,
      "ratioYearId": null
    },
    {
      "year": "2024",
      "quarter": 5,
      "ratioTTMId": 12280268,
      "ratioType": "RATIO_YEAR",
      "organCode": "MDG",
      "yearReport": 2024,
      "numberOfSharesMktCap": 10324781,
      "marketCap": 153839236900.0,
      "dividendYield": 0.0,
      "pe": 57.5040978773,
      "pb": 1.7558479021,
      "ps": 0.9999921195,
      "priceToCashFlow": 5.7540088536,
      "evToEbitda": 18.8910754876,
      "cashRatio": 0.1200656495,
      "quickRatio": 1.0443307558,
      "currentRatio": 1.1486224539,
      "ownersEquity": 0.0,
      "debtPerEquity": 0.6244968963,
      "debtToEquity": 1.5029975003,
      "roe": 0.0310077086,
      "roa": 0.0116795181,
      "daySaleOutstanding": 135.0984505303,
      "daysInventoryOutstanding": 46.5473863038,
      "daysPayableOutstanding": 167.4609066187,
      "grossMargin": 0.2323671009,
      "ebitMargin": 0.0494368303,
      "preTaxProfitMargin": 0.0177449399,
      "afterTaxProfitMargin": 0.017389928,
      "assetTurnover": 0.6716254464,
      "netInterestMargin": 0.0,
      "averageYieldOnEarningAssets": 0.0,
      "averageCostOfFinancing": 0.0,
      "nonAndInterestIncome": 0.0,
      "costToIncome": 0.0,
      "loansGrowth": 0.0,
      "depositGrowth": 0.0,
      "equityToLiabilities": 0.0,
      "equityToLoans": 0.0,
      "totalEquityTotalAsset": 0.0,
      "ldrLoanDepositRatio": 0.0,
      "npl": 0.0,
      "loansLossReservesToNPLs": 0.0,
      "loansLossReserveToLoans": 0.0,
      "provisionToOutstandingLoans": 0.0,
      "ebit": 11304791812.0,
      "ebitda": 15184156791.0,
      "roic": 0.0534345365,
      "cashCycle": 534.8564984113,
      "fixedAssetTurnover": 10.7441868091,
      "financialLeverage": 1.5029975003,
      "cir": 0.0,
      "car": null,
      "equity": null,
      "casaRatio": null,
      "nob66": null,
      "nob69": null,
      "nob70": null,
      "bsb113": 0.0,
      "ratioYearId": 12280268
    },
    {
      "year": "2025",
      "quarter": 1,
      "ratioTTMId": 2820384,
      "ratioType": "RATIO_TTM",
      "organCode": "MDG",
      "yearReport": 2025,
      "numberOfSharesMktCap": 10324781,
      "marketCap": 150741802600.0,
      "dividendYield": 0.0,
      "pe": 6.7699292854,
      "pb": 1.1329742207,
      "ps": 0.696035438,
      "priceToCashFlow": 2.1356447578,
      "evToEbitda": 6.659881093,
      "cashRatio": 0.0849962345,
      "quickRatio": 0.9527097181,
      "currentRatio": 1.0176604817,
      "ownersEquity": 0.0,
      "debtPerEquity": 0.6177644615,
      "debtToEquity": 1.3540366769,
      "roe": 0.1811951251,
      "roa": 0.0695909939,
      "daySaleOutstanding": 118.3073391078,
      "daysInventoryOutstanding": 38.3593988922,
      "daysPayableOutstanding": 161.5352738722,
      "grossMargin": 0.3192083992,
      "ebitMargin": 0.1335531006,
      "preTaxProfitMargin": 0.1030520381,
      "afterTaxProfitMargin": 0.1028128077,
      "assetTurnover": 0.6768708629,
      "netInterestMargin": 0.0,
      "averageYieldOnEarningAssets": 0.0,
      "averageCostOfFinancing": 0.0,
      "nonAndInterestIncome": 0.0,
      "costToIncome": 0.0,
      "loansGrowth": 0.0,
      "depositGrowth": 0.0,
      "equityToLiabilities": 0.0,
      "equityToLoans": 0.0,
      "totalEquityTotalAsset": 0.0,
      "ldrLoanDepositRatio": 0.0,
      "npl": 0.0,
      "loansLossReservesToNPLs": 0.0,
      "loansLossReserveToLoans": 0.0,
      "provisionToOutstandingLoans": 0.0,
      "ebit": 28923865113.0,
      "ebitda": 32691083749.0,
      "roic": 0.1343777486,
      "cashCycle": 510.9800105792,
      "fixedAssetTurnover": 11.0533768615,
      "financialLeverage": 1.3540366769,
      "cir": 0.0,
      "car": null,
      "equity": null,
      "casaRatio": null,
      "nob66": null,
      "nob69": null,
      "nob70": null,
      "bsb113": 0.0,
      "ratioYearId": null
    },
    {
      "year": "2025",
      "quarter": 2,
      "ratioTTMId": 2823802,
      "ratioType": "RATIO_TTM",
      "organCode": "MDG",
      "yearReport": 2025,
      "numberOfSharesMktCap": 10324781,
      "marketCap": 196170839000.0,
      "dividendYield": 0.0,
      "pe": 9.3411792555,
      "pb": 1.4723974724,
      "ps": 1.075235496,
      "priceToCashFlow": 5.9273405725,
      "evToEbitda": 8.2379272206,
      "cashRatio": 0.0249901315,
      "quickRatio": 0.8619084308,
      "currentRatio": 0.9422182253,
      "ownersEquity": 0.0,
      "debtPerEquity": 0.5118872299,
      "debtToEquity": 1.2812990797,
      "roe": 0.1638969034,
      "roa": 0.0667331913,
      "daySaleOutstanding": 130.7730665791,
      "daysInventoryOutstanding": 43.8234674222,
      "daysPayableOutstanding": 176.4695172278,
      "grossMargin": 0.3357065852,
      "ebitMargin": 0.1530642409,
      "preTaxProfitMargin": 0.1151070402,
      "afterTaxProfitMargin": 0.1151070402,
      "assetTurnover": 0.5797489988,
      "netInterestMargin": 0.0,
      "averageYieldOnEarningAssets": 0.0,
      "averageCostOfFinancing": 0.0,
      "nonAndInterestIncome": 0.0,
      "costToIncome": 0.0,
      "loansGrowth": 0.0,
      "depositGrowth": 0.0,
      "equityToLiabilities": 0.0,
      "equityToLoans": 0.0,
      "totalEquityTotalAsset": 0.0,
      "ldrLoanDepositRatio": 0.0,
      "npl": 0.0,
      "loansLossReservesToNPLs": 0.0,
      "loansLossReserveToLoans": 0.0,
      "provisionToOutstandingLoans": 0.0,
      "ebit": 27925734098.0,
      "ebitda": 31591081531.0,
      "roic": 0.1386359342,
      "cashCycle": 551.4854298891,
      "fixedAssetTurnover": 9.8317615746,
      "financialLeverage": 1.2812990797,
      "cir": 0.0,
      "car": null,
      "equity": null,
      "casaRatio": null,
      "nob66": null,
      "nob69": null,
      "nob70": null,
      "bsb113": 0.0,
      "ratioYearId": null
    },
    {
      "year": "2025",
      "quarter": 3,
      "ratioTTMId": 2824874,
      "ratioType": "RATIO_TTM",
      "organCode": "MDG",
      "yearReport": 2025,
      "numberOfSharesMktCap": 10324781,
      "marketCap": 216820401000.0,
      "dividendYield": 0.0,
      "pe": 7.0080301323,
      "pb": 1.4755232421,
      "ps": 1.1144891646,
      "priceToCashFlow": -8.9370270139,
      "evToEbitda": 6.9547330875,
      "cashRatio": 0.0876786344,
      "quickRatio": 0.9094283891,
      "currentRatio": 1.0218066227,
      "ownersEquity": 0.0,
      "debtPerEquity": 0.5070419113,
      "debtToEquity": 1.1697230454,
      "roe": 0.2277176707,
      "roa": 0.0980668767,
      "daySaleOutstanding": 113.7144642866,
      "daysInventoryOutstanding": 43.3442657925,
      "daysPayableOutstanding": 148.6564087724,
      "grossMargin": 0.3470606097,
      "ebitMargin": 0.1903312042,
      "preTaxProfitMargin": 0.1590303043,
      "afterTaxProfitMargin": 0.1590303043,
      "assetTurnover": 0.6166552794,
      "netInterestMargin": 0.0,
      "averageYieldOnEarningAssets": 0.0,
      "averageCostOfFinancing": 0.0,
      "nonAndInterestIncome": 0.0,
      "costToIncome": 0.0,
      "loansGrowth": 0.0,
      "depositGrowth": 0.0,
      "equityToLiabilities": 0.0,
      "equityToLoans": 0.0,
      "totalEquityTotalAsset": 0.0,
      "ldrLoanDepositRatio": 0.0,
      "npl": 0.0,
      "loansLossReservesToNPLs": 0.0,
      "loansLossReserveToLoans": 0.0,
      "provisionToOutstandingLoans": 0.0,
      "ebit": 37028343854.0,
      "ebitda": 39724826795.0,
      "roic": 0.1672071595,
      "cashCycle": 469.892828022,
      "fixedAssetTurnover": 11.0866349571,
      "financialLeverage": 1.1697230454,
      "cir": 0.0,
      "car": null,
      "equity": null,
      "casaRatio": null,
      "nob66": null,
      "nob69": null,
      "nob70": null,
      "bsb113": 0.0,
      "ratioYearId": null
    }
  ]
}